enot_vp/__init__.py
enot_vp/video_processor.py
enot_vp/backend/pyav.py
enot_vp-1.0.1.dist-info/METADATA
enot_vp-1.0.1.dist-info/WHEEL
enot_vp-1.0.1.dist-info/licenses/LICENSE
enot_vp-1.0.1.dist-info/RECORD
