Metadata-Version: 2.4
Name: enot-vp
Version: 1.0.1
Summary: ENOT video processor package for iterating over video frames easily.
Project-URL: Repository, https://github.com/Ruhrozz/enot-vp.git
Author-email: Malofeev Ivan <ruhrozz@bk.ru>
License-Expression: MIT
License-File: LICENSE
Classifier: Operating System :: OS Independent
Classifier: Programming Language :: Python :: 3
Requires-Python: >=3.9
Requires-Dist: av>=14.4.0
Requires-Dist: numpy>=1.21.0
